{
  "info": {
    "_postman_id": "68dec725-772e-4905-9e4b-6cc9dfd240d5",
    "name": "Parcial 2",
    "schema": "https://schema.getpostman.com/json/collection/v2.1.0/collection.json",
    "_exporter_id": "39214456",
    "_collection_link": "https://go.postman.co/collection/39214456-68dec725-772e-4905-9e4b-6cc9dfd240d5?source=collection_link"
  },
  "item": [
    {
      "name": "Magic Provider",
      "item": [
        {
          "name": "Create Magic Provider",
          "request": {
            "method": "POST",
            "header": [],
            "body": {
              "mode": "raw",
              "raw": "{\r\n    \"name\": \"Rafael\",\r\n    \"type\": \"POCION\"\r\n}",
              "options": {
                "raw": {
                  "language": "json"
                }
              }
            },
            "url": {
              "raw": "http://localhost:8080/api/magicProvider/providers",
              "protocol": "http",
              "host": [
                "localhost"
              ],
              "port": "8080",
              "path": [
                "api",
                "magicProvider",
                "providers"
              ]
            }
          },
          "response": []
        },
        {
          "name": "Get Magic Provider",
          "protocolProfileBehavior": {
            "disableBodyPruning": true
          },
          "request": {
            "method": "GET",
            "header": [],
            "body": {
              "mode": "raw",
              "raw": "{\r\n    \"name\": \"Rafael\",\r\n    \"type\": \"POCION\"\r\n}"
            },
            "url": {
              "raw": "http://localhost:8080/api/magicProvider/providers/2",
              "protocol": "http",
              "host": [
                "localhost"
              ],
              "port": "8080",
              "path": [
                "api",
                "magicProvider",
                "providers",
                "2"
              ]
            }
          },
          "response": []
        },
        {
          "name": "Delete Magic Provider",
          "request": {
            "method": "DELETE",
            "header": [],
            "body": {
              "mode": "raw",
              "raw": "{\r\n    \"name\": \"Rafael\",\r\n    \"type\": \"POCION\"\r\n}"
            },
            "url": {
              "raw": "http://localhost:8080/api/magicProvider/providers/2",
              "protocol": "http",
              "host": [
                "localhost"
              ],
              "port": "8080",
              "path": [
                "api",
                "magicProvider",
                "providers",
                "2"
              ]
            }
          },
          "response": []
        },
        {
          "name": "Update Magic Provider",
          "request": {
            "method": "PUT",
            "header": [],
            "body": {
              "mode": "raw",
              "raw": "{\r\n    \"name\": \"Rafael Gutierrez\",\r\n    \"type\": \"POCION\"\r\n}",
              "options": {
                "raw": {
                  "language": "json"
                }
              }
            },
            "url": {
              "raw": "http://localhost:8080/api/magicProvider/providers/2",
              "protocol": "http",
              "host": [
                "localhost"
              ],
              "port": "8080",
              "path": [
                "api",
                "magicProvider",
                "providers",
                "2"
              ]
            }
          },
          "response": []
        }
      ]
    },
    {
      "name": "Magic Article",
      "item": [
        {
          "name": "Create Magic Article",
          "request": {
            "method": "POST",
            "header": [],
            "body": {
              "mode": "raw",
              "raw": "{\r\n    \"name\": \"Espada de rayo\",\r\n    \"type\": \"POCION\",\r\n    \"price\": 3,\r\n    \"magicProviderId\": 5\r\n}\r\n",
              "options": {
                "raw": {
                  "language": "json"
                }
              }
            },
            "url": {
              "raw": "http://localhost:8080/api/magicArticle/artefacts",
              "protocol": "http",
              "host": [
                "localhost"
              ],
              "port": "8080",
              "path": [
                "api",
                "magicArticle",
                "artefacts"
              ]
            }
          },
          "response": []
        },
        {
          "name": "Update Magic Article",
          "request": {
            "method": "PUT",
            "header": [],
            "body": {
              "mode": "raw",
              "raw": "{\r\n    \"name\": \"Espada de hielo\",\r\n    \"type\": \"POCION\",\r\n    \"price\": 1,\r\n    \"magicProviderId\": 5\r\n}\r\n",
              "options": {
                "raw": {
                  "language": "json"
                }
              }
            },
            "url": {
              "raw": "http://localhost:8080/api/magicArticle/artefacts/2",
              "protocol": "http",
              "host": [
                "localhost"
              ],
              "port": "8080",
              "path": [
                "api",
                "magicArticle",
                "artefacts",
                "2"
              ]
            }
          },
          "response": []
        },
        {
          "name": "Get Artefact",
          "protocolProfileBehavior": {
            "disableBodyPruning": true
          },
          "request": {
            "method": "GET",
            "header": [],
            "body": {
              "mode": "raw",
              "raw": "{\r\n    \"name\": \"Rafael Gutierrez\",\r\n    \"type\": \"POCION\"\r\n}"
            },
            "url": {
              "raw": "http://localhost:8080/api/magicArticle/artefacts/3",
              "protocol": "http",
              "host": [
                "localhost"
              ],
              "port": "8080",
              "path": [
                "api",
                "magicArticle",
                "artefacts",
                "3"
              ]
            }
          },
          "response": []
        },
        {
          "name": "Delete Magic Article",
          "request": {
            "method": "DELETE",
            "header": [],
            "url": {
              "raw": "http://localhost:8080/api/magicArticle/artefacts/1",
              "protocol": "http",
              "host": [
                "localhost"
              ],
              "port": "8080",
              "path": [
                "api",
                "magicArticle",
                "artefacts",
                "1"
              ]
            }
          },
          "response": []
        }
      ]
    }
  ]
}